scr/mult.v
module mult(
    input [3:0] a,
    input [3:0] b,
    input clk,
    input init,
    output reg [7:0] result,
    output reg done
);
    
    parameter star   = 3'b000;
    parameter check  = 3'b001;
    parameter add    = 3'b010;
    parameter shift  = 3'b011;
    parameter finish = 3'b100;

    reg [2:0] state, next_state;
    reg [7:0] pp;
    reg [7:0] a_copy, b_copy;

    always @(posedge clk) begin
        if (init)
            state <= star;
        else
            state <= next_state;
    end

    always @(*) begin
        case(state)
            star:   next_state = check;
            check:  next_state = (b_copy[0] == 1'b1) ? add : shift;
            add:    next_state = shift;
            shift:  next_state = (b_copy == 0) ? finish : check;
            finish: next_state = finish;
            default:next_state = star;
        endcase
    end
    
    always @(posedge clk) begin
        if (init) begin
            pp      <= 8'b0;
            a_copy  <= {4'b0000, a};  
            b_copy  <= {4'b0000, b}; 
            result  <= 8'b0;
            done    <= 1'b0;
        end else begin
            case(state)
                star: begin
                    pp     <= 8'b0;
                    a_copy <= {4'b000, a}; 
                    b_copy <= {4'b000, b};
                    done   <= 1'b0;
                end

                add: begin
                    pp <= pp + a_copy;
                end

                shift: begin
                    a_copy <= a_copy << 1;
                    b_copy <= b_copy >> 1;
                end

                finish: begin
                    result <= pp;
                    done   <= 1'b1;
                end
            endcase
        end
    end

endmodule

scr/shift.v
module shift(
input[3:0] a,
input [3:0] shift_,

output[6:0] shift_number,
output done
);

assign shift_number = a<<shift_;
assign done = 1'b1;

endmodule

scr/adder.v
module adder(
    input a,
    input b,
    input cin,
    output sum,
    output carry
);

    wire ab_xor, and1, and2;

xor(ab_xor, a, b);
xor(sum, ab_xor, cin);

and(and1, a, b);
and(and2, cin, ab_xor);

or (carry, and1, and2);

endmodule

four_adder.v
module four_adder(
input[3:0] a,
input [3:0] b,
input clk,
input cin,
output[3:0] sum,
output carry
);


wire in0,in1,in2,in3;

wire carry0, carry1, carry2;

xor(in0,b[0],cin);
xor(in1,b[1],cin);
xor(in2,b[2],cin);
xor(in3,b[3],cin);

adder ad0(
.a(a[0]),
.b(in0),
.cin(cin),
.sum(sum[0]),
.carry(carry0)
);

adder ad1(
.a(a[1]),
.b(in1),
.cin(carry0),
.sum(sum[1]),
.carry(carry1)
);

adder ad2(
.a(a[2]),
.b(in2),
.cin(carry1),
.sum(sum[2]),
.carry(carry2)
);

adder ad3(
.a(a[3]),
.b(in3),
.cin(carry2),
.sum(sum[3]),
.carry(carry)
); 
endmodule

scr/alu.v
`include "four_adder.v"
`include "adder.v"
`include "mult.v"
`include "shift.v"

module alu(
    input clk,
    input [3:0] a,
    input [3:0] b,
    input [2:0] op,
    input init,
    input cin,
    
    output reg [6:0] result,
    output reg carry,
    output reg done,
    output reg overflow,
    output reg zero
);

    wire done_;
    wire carry_;
    wire [3:0] sum_;
    wire [6:0] sum_result = {carry_, sum_};
    wire [7:0] mul_result;
    wire [6:0] shift_w;
    wire [6:0] rest_result = {2'b00, sum_};
    reg [6:0] temp_result;

    // Instancias
    four_adder sum(
        .a(a),
        .b(b),
        .cin(cin),
        .sum(sum_),
        .carry(carry_)
    );

    shift sh(
        .a(a),
        .shift_(b),
        .shift_number(shift_w),
        .done(done_)
    );

    mult mul(
        .a(a),
        .b(b),
        .clk(clk),
        .init(init),
        .result(mul_result),
        .done(done_)
    );

    always @(posedge clk) begin
        
        if (init) begin
            result <= 7'b0000000;
            overflow <= 1'b0;
            done <= 1'b0;
            carry <= 1'b0;
            zero <= 1'b0;

        end else begin
            temp_result = 7'b0000000;
            overflow = 1'b0;
            carry = 1'b0;
            done = 1'b0;

            case (op)
                3'b001: begin // Suma
                    if (cin) begin
                        temp_result = rest_result;
                        carry = carry_;

                    end else begin
                        temp_result = sum_result;
                        carry = carry_;
                    end
                end

                3'b010: begin // Multiplicación
                    temp_result = mul_result[6:0];
                    overflow = mul_result[7];
                    done = done_;
                end

                3'b011: begin // Desplazamiento
                    temp_result = shift_w;
                    done = done_;
                end

                3'b111: begin // Operación lógica: AND
                    temp_result = a & b;
                    done = done_;
                end

                default: begin
                    temp_result = 7'b0000000;
                    overflow = 1'b0;
                end
            endcase

            // Salidas 
            result <= temp_result;
            zero <= (temp_result == 0);
            carry <= carry;
            overflow <= overflow;
            done <= done;
        end
    end

endmodule

scr/alu_tb.v

`timescale 1ns / 1ps

module alu_tb;

    // Entradas
    reg clk;
    reg [3:0] a;
    reg [3:0] b;
    reg [2:0] op;
    reg init;
    reg cin;
    wire overflow;

    // Salidas
    wire [6:0] result;
    wire carry;
    wire done;
    wire zero;

    // Instancia del módulo ALU
    alu uut (
        .clk(clk),
        .a(a),
        .b(b),
        .op(op),
        .init(init),
        .cin(cin),
        .result(result),
        .carry(carry),
        .done(done),
        .overflow(overflow),
        .zero(zero)
    );

    // Reloj: alterna cada 5 ns (periodo de 10 ns)
    always #5 clk = ~clk;

    initial begin
        // VCD para GTKWave
        $dumpfile("alu_tb.vcd");
        $dumpvars(0, alu_tb);

        // Inicialización
        clk = 0;
        a = 0;
        b = 0;
        op = 3'b000;
        init = 1;
        cin = 0;
        init = 0;

        // Espera inicial
        #10;

        
        // --- TEST 1: Suma (8 + 9 = 17) -> Genera carry out ---
        op = 3'b001;
        a = 4'b1000;
        b = 4'b1001;
        cin = 0;
        #20;
        

        init = 1;
        a = 4'b1111;
        b = 4'b1111;
        #10;
        // --- TEST 2: Multiplicación (15 * 15 = 225) -> Genera overflow ---
        op = 3'b010;
        init = 0;
        // Esperar hasta que el multiplicador indique que terminó
        wait (done == 1);
        #20;

        
        init = 1;
        a = 4'b1100;
        b = 4'b1101;
        #10;
        // --- TEST 3: Suma con carry de salida (12 + 13 = 25) ---
        init = 0;
        op = 3'b001;
        cin = 0;
        #20;

        init = 1;
        a = 4'b1001;
        b = 4'b0100;
        cin = 1;  // Pasa a B a su complemento a 2
        #10;
        // --- TEST 4: Resta simulada (9 - 4 = 5) usando complemento a 2 ---
        init = 0;
        op = 3'b001;    
        #20;
        cin = 0;


        // --- TEST 5: Operación lógica AND ---
        op = 3'b111;
        a = 4'b1011;
        b = 4'b1110;
        #20;


        #10;
        // TEST 6: Desplazamiento de 1011 un total de 10 veces (Activa bandera de zero)---
        op = 3'b011;
        a = 4'b1011;
        b = 4'b1000;
        #20;      


        init = 1;
        #10;
        // TEST 7: Multiplicación (14 * 0 = 225) -> Activa bandera de zero ---
        op = 3'b010;
        a = 4'b1110;
        b = 4'b0000;
        init = 0;
        // Esperar hasta que el multiplicador indique que terminó
        wait (done == 1);
        #20;


        // --- TEST 8: Resta simulada (9 - 4 = 5) usando complemento a 2 ---
        cin = 1;
        op = 3'b001;
        a = 4'b0010;
        b = 4'b0011;
        #20;
        cin = 0;


        // --- TEST 9: Operación lógica AND ---
        op = 3'b111;
        a = 4'b1010;
        b = 4'b0101;
        #20;


        init = 1;
        #10;
        // TEST 10: Multiplicación (12 * 10 = 120) -> NO Activa bandera de overflow ---
        op = 3'b010;
        init = 0;
        a = 4'b1100;
        b = 4'b1010;
        // Esperar hasta que el multiplicador indique que terminó
        wait (done == 1);
        #20;

        

        init = 1;
        #10;
        // TEST 11: Multiplicación (13 * 10 = 120) -> SI Activa bandera de overflow ---
        op = 3'b010;
        a = 4'b1101;
        b = 4'b1010;
        init = 0;
        // Esperar hasta que el multiplicador indique que terminó
        wait (done == 1);
        #20;


        // TEST 12: Desplazamiento de 1011 un total de 3 veces (Activa bandera de zero)---
        op = 3'b011;
        a = 4'b1011;
        b = 4'b0011;
        #100;       


        $display("=== Fin del test ===");
        $finish;
    end

endmodule

scr/alu_tb.vcd
$date
	Sun Oct 12 13:51:47 2025
$end
$version
	Icarus Verilog
$end
$timescale
	1ps
$end
$scope module alu_tb $end
$var wire 1 ! zero $end
$var wire 7 " result [6:0] $end
$var wire 1 # overflow $end
$var wire 1 $ done $end
$var wire 1 % carry $end
$var reg 4 & a [3:0] $end
$var reg 4 ' b [3:0] $end
$var reg 1 ( cin $end
$var reg 1 ) clk $end
$var reg 1 * init $end
$var reg 3 + op [2:0] $end
$scope module uut $end
$var wire 4 , a [3:0] $end
$var wire 4 - b [3:0] $end
$var wire 1 ( cin $end
$var wire 1 ) clk $end
$var wire 1 . done_ $end
$var wire 1 * init $end
$var wire 3 / op [2:0] $end
$var wire 7 0 sum_result [6:0] $end
$var wire 4 1 sum_ [3:0] $end
$var wire 7 2 shift_w [6:0] $end
$var wire 7 3 rest_result [6:0] $end
$var wire 8 4 mul_result [7:0] $end
$var wire 1 5 carry_ $end
$var reg 1 % carry $end
$var reg 1 $ done $end
$var reg 1 # overflow $end
$var reg 7 6 result [6:0] $end
$var reg 7 7 temp_result [6:0] $end
$var reg 1 ! zero $end
$scope module mul $end
$var wire 4 8 a [3:0] $end
$var wire 4 9 b [3:0] $end
$var wire 1 ) clk $end
$var wire 1 * init $end
$var parameter 3 : add $end
$var parameter 3 ; check $end
$var parameter 3 < finish $end
$var parameter 3 = shift $end
$var parameter 3 > star $end
$var reg 8 ? a_copy [7:0] $end
$var reg 8 @ b_copy [7:0] $end
$var reg 1 A done $end
$var reg 3 B next_state [2:0] $end
$var reg 8 C pp [7:0] $end
$var reg 8 D result [7:0] $end
$var reg 3 E state [2:0] $end
$upscope $end
$scope module sh $end
$var wire 4 F a [3:0] $end
$var wire 1 . done $end
$var wire 4 G shift_ [3:0] $end
$var wire 7 H shift_number [6:0] $end
$upscope $end
$scope module sum $end
$var wire 4 I a [3:0] $end
$var wire 4 J b [3:0] $end
$var wire 1 ( cin $end
$var wire 1 K clk $end
$var wire 1 L in0 $end
$var wire 1 M in1 $end
$var wire 1 N in2 $end
$var wire 1 O in3 $end
$var wire 4 P sum [3:0] $end
$var wire 1 Q carry2 $end
$var wire 1 R carry1 $end
$var wire 1 S carry0 $end
$var wire 1 5 carry $end
$scope module ad0 $end
$var wire 1 T a $end
$var wire 1 U ab_xor $end
$var wire 1 V and1 $end
$var wire 1 W and2 $end
$var wire 1 L b $end
$var wire 1 S carry $end
$var wire 1 ( cin $end
$var wire 1 X sum $end
$upscope $end
$scope module ad1 $end
$var wire 1 Y a $end
$var wire 1 Z ab_xor $end
$var wire 1 [ and1 $end
$var wire 1 \ and2 $end
$var wire 1 M b $end
$var wire 1 R carry $end
$var wire 1 S cin $end
$var wire 1 ] sum $end
$upscope $end
$scope module ad2 $end
$var wire 1 ^ a $end
$var wire 1 _ ab_xor $end
$var wire 1 ` and1 $end
$var wire 1 a and2 $end
$var wire 1 N b $end
$var wire 1 Q carry $end
$var wire 1 R cin $end
$var wire 1 b sum $end
$upscope $end
$scope module ad3 $end
$var wire 1 c a $end
$var wire 1 d ab_xor $end
$var wire 1 e and1 $end
$var wire 1 f and2 $end
$var wire 1 O b $end
$var wire 1 5 carry $end
$var wire 1 Q cin $end
$var wire 1 g sum $end
$upscope $end
$upscope $end
$upscope $end
$upscope $end
$enddefinitions $end
$comment Show the parameter values. $end
$dumpall
b0 >
b11 =
b100 <
b1 ;
b10 :
$end
#0
$dumpvars
0g
0f
0e
0d
0c
0b
0a
0`
0_
0^
0]
0\
0[
0Z
0Y
0X
0W
0V
0U
0T
0S
0R
0Q
b0 P
0O
0N
0M
0L
zK
b0 J
b0 I
b0 H
b0 G
b0 F
bx E
bx D
bx C
bx B
xA
bx @
bx ?
b0 9
b0 8
bx 7
bx 6
05
bx 4
b0 3
b0 2
b0 1
b0 0
b0 /
x.
b0 -
b0 ,
b0 +
0*
0)
0(
b0 '
b0 &
x%
x$
x#
bx "
x!
$end
#5000
1!
b0 "
b0 6
0$
0%
0#
b0 7
1)
#10000
1X
15
1U
1e
b1 3
b10001 0
b1 1
b1 P
0g
1L
1O
0d
1c
0)
b1001 '
b1001 -
b1001 9
b1001 G
b1001 J
b0 2
b0 H
b1000 &
b1000 ,
b1000 8
b1000 F
b1000 I
b1 +
b1 /
#15000
0!
b10001 "
b10001 6
1%
b10001 7
1)
#20000
0)
#25000
1%
b10001 7
1)
#30000
1g
1R
1Q
1[
1`
0X
1S
1]
b1110 3
b11110 0
b1110 1
b1110 P
1b
1M
1N
0U
1V
0Z
0_
1T
1Y
1^
0)
b1111 '
b1111 -
b1111 9
b1111 G
b1111 J
b1111 &
b1111 ,
b1111 8
b1111 F
b1111 I
1*
#35000
b1 B
0%
b0 "
b0 6
0A
b0 4
b0 D
b1111 @
b1111 ?
b0 C
b0 E
1)
#40000
0)
0*
b10 +
b10 /
#45000
b10 B
b1 E
1!
x$
b0 7
1)
#50000
0)
#55000
b11 B
b10 E
x$
1)
#60000
0)
#65000
b1 B
b11 E
b1111 C
x$
1)
#70000
0)
#75000
b10 B
b111 @
b11110 ?
b1 E
x$
1)
#80000
0)
#85000
b11 B
b10 E
x$
1)
#90000
0)
#95000
b1 B
b101101 C
b11 E
x$
1)
#100000
0)
#105000
b10 B
b1 E
b11 @
b111100 ?
x$
1)
#110000
0)
#115000
b11 B
b10 E
x$
1)
#120000
0)
#125000
b1 B
b11 E
b1101001 C
x$
1)
#130000
0)
#135000
b10 B
b1 @
b1111000 ?
b1 E
x$
1)
#140000
0)
#145000
b11 B
b10 E
x$
1)
#150000
0)
#155000
b1 B
b11100001 C
b11 E
x$
1)
#160000
0)
#165000
b11 B
b1 E
b0 @
b11110000 ?
x$
1)
#170000
0)
#175000
b100 B
b11 E
x$
1)
#180000
0)
#185000
b100 E
b11100000 ?
x$
1)
#190000
0)
#195000
1.
1A
b11100001 4
b11100001 D
x$
1)
#200000
0)
#205000
0!
b1100001 "
b1100001 6
1#
b1100001 7
1$
1)
#210000
0)
#215000
1$
1#
b1100001 7
1)
#220000
0)
#225000
b1 B
b0 E
x.
0A
b0 4
b0 D
b1101 @
b1100 ?
b0 C
0$
0#
b0 "
b0 6
0b
1X
0S
b1001 3
b11001 0
b1001 1
b1001 P
0]
0\
0R
0M
1U
0V
0Z
0[
0T
0Y
1)
b1101 '
b1101 -
b1101 9
b1101 G
b1101 J
b1100 &
b1100 ,
b1100 8
b1100 F
b1100 I
1*
#230000
0)
#235000
b10 B
b11001 "
b11001 6
b1 E
1%
b11001 7
1)
b1 +
b1 /
0*
#240000
0)
#245000
b11 B
b10 E
1%
b11001 7
1)
#250000
0)
#255000
b1 B
0%
b0 "
b0 6
b100 @
b1001 ?
b0 E
1b
1R
0g
1\
0Q
1Z
1S
0U
1V
0`
1M
0N
b101 3
b10101 0
b101 1
b101 P
1X
0W
1T
0^
1)
1(
b10000 2
b10000 H
b100 '
b100 -
b100 9
b100 G
b100 J
b1001 &
b1001 ,
b1001 8
b1001 F
b1001 I
1*
#260000
0)
#265000
b11 B
b1 E
b101 "
b101 6
1%
b101 7
1)
0*
#270000
0)
#275000
b1 B
b11 E
1%
b101 7
1)
#280000
0)
#285000
b11 B
b1 E
b10 @
b10010 ?
b1010 "
b1010 6
0\
1Q
0Z
1[
0S
0b
1a
1g
15
1U
0V
1_
0d
1e
x$
0%
b1010 7
1Y
0L
1M
1N
1O
b1001 3
b11001 0
b1001 1
b1001 P
1X
1)
b1110 '
b1110 -
b1110 9
b1110 G
b1110 J
b0 2
b0 H
b1011 &
b1011 ,
b1011 8
b1011 F
b1011 I
b111 +
b111 /
0(
#290000
0)
#295000
b1 B
b11 E
x$
b1010 7
1)
#300000
0)
#305000
b10 B
b1 E
b1 @
b100100 ?
x$
b1010 7
1)
#310000
0)
#315000
b11 B
1!
b0 "
b0 6
b10 E
0g
0Q
1]
0R
b11 3
b10011 0
b11 1
b11 P
0b
0a
1Z
0[
0_
0M
0N
x$
b0 7
1)
b1000 '
b1000 -
b1000 9
b1000 G
b1000 J
b11 +
b11 /
#320000
0)
#325000
b1 B
b11 E
b100100 C
x$
1)
#330000
0)
#335000
0!
0$
b1000 @
b1011 ?
b0 C
b0 E
1)
1*
#340000
0)
#345000
b11 B
b1 E
b0 @
b1110 ?
1!
1g
05
1d
0e
0X
b1110 3
b1110 0
b1110 1
b1110 P
1b
0O
0U
1_
x$
0T
1^
1)
0*
b1110 2
b1110 H
b0 '
b0 -
b0 9
b0 G
b0 J
b1110 &
b1110 ,
b1110 8
b1110 F
b1110 I
b10 +
b10 /
#350000
0)
#355000
b100 B
b11 E
x$
1)
#360000
0)
#365000
b100 E
b11100 ?
x$
1)
#370000
0)
#375000
1.
1A
x$
1)
#380000
0)
#385000
1$
1)
#390000
0)
#395000
1$
1)
#400000
0)
#405000
0!
b1111 "
b1111 6
05
1g
0f
0Q
0\
0S
1b
0a
0W
1]
0R
0U
1Z
0[
b1111 7
0$
0^
0c
0L
0M
1N
1O
b1111 3
b1111 0
b1111 1
b1111 P
1X
1)
b11 '
b11 -
b11 9
b11 G
b11 J
b10000 2
b10000 H
b10 &
b10 ,
b10 8
b10 F
b10 I
b1 +
b1 /
1(
#410000
0)
#415000
b1111 7
1)
#420000
0)
#425000
1!
b0 "
b0 6
05
1g
0f
0Q
0a
1]
0R
1b
1U
1Z
0[
1_
1$
b0 7
1c
1L
0M
1N
0O
b1111 3
b1111 0
b1111 1
b1111 P
1X
1)
b101 '
b101 -
b101 9
b101 G
b101 J
b1000000 2
b1000000 H
b1010 &
b1010 ,
b1010 8
b1010 F
b1010 I
b111 +
b111 /
0(
#430000
0)
#435000
1$
1)
#440000
0)
#445000
b1 B
b0 E
x.
0A
b101 @
b1010 ?
0!
0$
1)
1*
#450000
0)
#455000
b11 B
1!
b1010 @
b1100 ?
b1 E
0g
0X
15
0U
0d
1e
1]
b110 3
b10110 0
b110 1
b110 P
1b
0Q
0L
1M
0N
1O
1Z
1_
0`
x$
0Y
1^
1)
b1010 '
b1010 -
b1010 9
b1010 G
b1010 J
b0 2
b0 H
b1100 &
b1100 ,
b1100 8
b1100 F
b1100 I
0*
b10 +
b10 /
#460000
0)
#465000
b1 B
b11 E
x$
1)
#470000
0)
#475000
b10 B
b101 @
b11000 ?
b1 E
x$
1)
#480000
0)
#485000
b11 B
b10 E
x$
1)
#490000
0)
#495000
b1 B
b11000 C
b11 E
x$
1)
#500000
0)
#505000
b11 B
b1 E
b10 @
b110000 ?
x$
1)
#510000
0)
#515000
b1 B
b11 E
x$
1)
#520000
0)
#525000
b10 B
b1 E
b1 @
b1100000 ?
x$
1)
#530000
0)
#535000
b11 B
b10 E
x$
1)
#540000
0)
#545000
b1 B
b11 E
b1111000 C
x$
1)
#550000
0)
#555000
b11 B
b0 @
b11000000 ?
b1 E
x$
1)
#560000
0)
#565000
b100 B
b11 E
x$
1)
#570000
0)
#575000
b10000000 ?
b100 E
x$
1)
#580000
0)
#585000
1.
1A
b1111000 4
b1111000 D
x$
1)
#590000
0)
#595000
0!
b1111000 "
b1111000 6
b1111000 7
1$
1)
#600000
0)
#605000
1$
b1111000 7
1)
#610000
0)
#615000
b1 B
0$
b0 "
b0 6
x.
0A
b0 4
b0 D
b1010 @
b1100 ?
b0 C
b0 E
1)
1*
#620000
0)
#625000
b11 B
b1 E
b1101 ?
1!
b111 3
b10111 0
b111 1
b111 P
1X
1U
x$
b0 7
1T
1)
0*
b1101 &
b1101 ,
b1101 8
b1101 F
b1101 I
#630000
0)
#635000
b1 B
b11 E
x$
1)
#640000
0)
#645000
b10 B
b1 E
b101 @
b11010 ?
x$
1)
#650000
0)
#655000
b11 B
b10 E
x$
1)
#660000
0)
#665000
b1 B
b11 E
b11010 C
x$
1)
#670000
0)
#675000
b11 B
b10 @
b110100 ?
b1 E
x$
1)
#680000
0)
#685000
b1 B
b11 E
x$
1)
#690000
0)
#695000
b10 B
b1 @
b1101000 ?
b1 E
x$
1)
#700000
0)
#705000
b11 B
b10 E
x$
1)
#710000
0)
#715000
b1 B
b10000010 C
b11 E
x$
1)
#720000
0)
#725000
b11 B
b1 E
b0 @
b11010000 ?
x$
1)
#730000
0)
#735000
b100 B
b11 E
x$
1)
#740000
0)
#745000
b100 E
b10100000 ?
x$
1)
#750000
0)
#755000
1.
1A
b10000010 4
b10000010 D
x$
1)
#760000
0)
#765000
0!
b10 "
b10 6
1#
b10 7
1$
1)
#770000
0)
#775000
1$
1#
b10 7
1)
#780000
0)
#785000
b1011000 "
b1011000 6
0X
1S
1g
05
0U
1V
1d
0e
1]
1R
b1110 3
b1110 0
b1110 1
b1110 P
1b
1L
0O
0Z
1[
0_
1$
0#
b1011000 7
1Y
0^
1)
b1011000 2
b1011000 H
b11 '
b11 -
b11 9
b11 G
b11 J
b1011 &
b1011 ,
b1011 8
b1011 F
b1011 I
b11 +
b11 /
#790000
0)
#795000
1$
b1011000 7
1)
#800000
0)
#805000
1$
b1011000 7
1)
#810000
0)
#815000
1$
b1011000 7
1)
#820000
0)
#825000
1$
b1011000 7
1)
#830000
0)
#835000
1$
b1011000 7
1)
#840000
0)
#845000
1$
b1011000 7
1)
#850000
0)
#855000
1$
b1011000 7
1)
#860000
0)
#865000
1$
b1011000 7
1)
#870000
0)
#875000
1$
b1011000 7
1)
#880000
0)
#885000
1$
b1011000 7
1)
