scr/mult.v
module mult(
    input [3:0] a,
    input [3:0] b,
    input clk,
    input init,
    output reg [7:0] result,
    output reg done
);
    
    parameter star   = 3'b000;
    parameter check  = 3'b001;
    parameter add    = 3'b010;
    parameter shift  = 3'b011;
    parameter finish = 3'b100;

    reg [2:0] state, next_state;
    reg [7:0] pp;
    reg [7:0] a_copy, b_copy;

    always @(posedge clk) begin
        if (init)
            state <= star;
        else
            state <= next_state;
    end

    always @(*) begin
        case(state)
            star:   next_state = check;
            check:  next_state = (b_copy[0] == 1'b1) ? add : shift;
            add:    next_state = shift;
            shift:  next_state = (b_copy == 0) ? finish : check;
            finish: next_state = finish;
            default:next_state = star;
        endcase
    end
    
    always @(posedge clk) begin
        if (init) begin
            pp      <= 8'b0;
            a_copy  <= {4'b0000, a};  
            b_copy  <= {4'b0000, b}; 
            result  <= 8'b0;
            done    <= 1'b0;
        end else begin
            case(state)
                star: begin
                    pp     <= 8'b0;
                    a_copy <= {4'b000, a}; 
                    b_copy <= {4'b000, b};
                    done   <= 1'b0;
                end

                add: begin
                    pp <= pp + a_copy;
                end

                shift: begin
                    a_copy <= a_copy << 1;
                    b_copy <= b_copy >> 1;
                end

                finish: begin
                    result <= pp;
                    done   <= 1'b1;
                end
            endcase
        end
    end

endmodule

scr/shift.v
module shift(
input[3:0] a,
input [3:0] shift_,

output[6:0] shift_number,
output done
);

assign shift_number = a<<shift_;
assign done = 1'b1;

endmodule

scr/adder.v
module adder(
    input a,
    input b,
    input cin,
    output sum,
    output carry
);

    wire ab_xor, and1, and2;

xor(ab_xor, a, b);
xor(sum, ab_xor, cin);

and(and1, a, b);
and(and2, cin, ab_xor);

or (carry, and1, and2);

endmodule

four_adder.v
module four_adder(
input[3:0] a,
input [3:0] b,
input clk,
input cin,
output[3:0] sum,
output carry
);


wire in0,in1,in2,in3;

wire carry0, carry1, carry2;

xor(in0,b[0],cin);
xor(in1,b[1],cin);
xor(in2,b[2],cin);
xor(in3,b[3],cin);

adder ad0(
.a(a[0]),
.b(in0),
.cin(cin),
.sum(sum[0]),
.carry(carry0)
);

adder ad1(
.a(a[1]),
.b(in1),
.cin(carry0),
.sum(sum[1]),
.carry(carry1)
);

adder ad2(
.a(a[2]),
.b(in2),
.cin(carry1),
.sum(sum[2]),
.carry(carry2)
);

adder ad3(
.a(a[3]),
.b(in3),
.cin(carry2),
.sum(sum[3]),
.carry(carry)
); 
endmodule

scr/alu.v
`include "four_adder.v"
`include "adder.v"
`include "mult.v"
`include "shift.v"

module alu(
    input clk,
    input [3:0] a  ,
    input [3:0] b ,
    input[2:0] op,
    input init,
    input cin,
    output reg [6:0] result,
    output reg carry,
    output reg done,
    output reg overflow,
    output reg zero
);

wire done_;
wire carry_;
wire [3:0] sum_;
wire [6:0] sum_result =   {carry_,sum_};
wire[7:0] mul_result;
wire[6:0] shift_w;
wire [6:0] rest_result =   {2'b00,sum_};
four_adder sum(
.a(a),
.b(b),
.cin(cin),
.sum(sum_),
.carry(carry_)
);

shift sh(
.a(a),
.shift_(b),
.shift_number(shift_w),
.done(done_)
);

mult mul(
.a(a),
.b(b),
.clk(clk),
.init(init),
.result(mul_result),
.done(done_)
);

            
always @(posedge clk) begin
    if (init) begin
        result   <= 7'b0000000;
        overflow <= 1'b0;
        done <= 1'b0;
        carry <= 1'b0;
        
    end else begin
        case (op)
            3'b001: begin // Suma

            if(cin) begin
              result <= rest_result;
              overflow <= 1'b0;
              carry <= carry_;
              zero <= (rest_result == 0) ? 1:0;

            end else begin 
                result   <= sum_result;
                overflow <= 1'b0;
                carry <= carry_;
                zero <= (sum_result == 0) ? 1:0; 
            end   
            end
            
            3'b010: begin // Multiplicación
                overflow <= mul_result[7]; 
                result   <= mul_result[6:0];
                zero <= (mul_result == 0) ? 1:0;
                done <= done_;
            end
            3'b011: begin
            result <= shift_w;
            zero <= (shift_w == 0) ? 1:0;
            done <= done_;
            end
            3'b111:begin 

                result <= a & b;
                zero <= (result == 0) ? 1:0;
                done <= done_;

            end
            default: begin
                result   <= 7'b0000000;
                overflow <= 1'b0;
            end
        endcase
    end
end


endmodule

scr/alu_tb.v

`timescale 1ns / 1ps

module alu_tb;

    // Entradas
    reg clk;
    reg [3:0] a;
    reg [3:0] b;
    reg [2:0] op;
    reg init;
    reg cin;
    wire overflow;

    // Salidas
    wire [6:0] result;
    wire carry;
    wire done;
    wire zero;

    // Instancia del módulo ALU
    alu dut (
        .clk(clk),
        .a(a),
        .b(b),
        .op(op),
        .init(init),
        .cin(cin),
        .result(result),
        .carry(carry),
        .done(done),
        .overflow(overflow),
        .zero(zero)
    );

    // Reloj: alterna cada 5 ns (periodo de 10 ns)
    always #5 clk = ~clk;

    initial begin
        // VCD para GTKWave
        $dumpfile("alu_tb.vcd");
        $dumpvars(0, alu_tb);

        // Inicialización
        clk = 0;
        a = 0;
        b = 0;
        op = 3'b000;
        init = 1;
        cin = 0;
        init = 0;

        // Espera inicial
        #10;

        // --- TEST 1: Suma (3 + 4 = 7) ---
        a = 4'd8;
        b = 4'd9;
        cin = 0;
        op = 3'b001;  // Suma
        #20;
        

        // --- TEST 2: Multiplicación (5 * 2 = 10) ---
        a = 4'b1111;
        b = 4'b1111;
        init = 1;
        #10;
        init = 0;
        op = 3'b010;  // Multiplicación
         #100;
        // Esperar hasta que el multiplicador indique que terminó
        wait (done == 1);
        #20;

        // --- TEST 3: Suma con carry (8 + 9 = 17) ---
        init = 1;
        #10;
        
        a = 4'b1000;
        b = 4'b1001;
        cin = 0;
        op = 3'b001;
        init = 0;
        #20;

        // --- TEST 4: Resta simulada (9 - 4 = 5) usando complemento a 2 ---
        a = 4'd9;
        b = 4'd4; // -4 en complemento a 2
        cin = 1;
        op = 3'b001;
        #200;

        a = 4'd11;
        b = 4'd14; // -4 en complemento a 2
        cin = 1;
        op = 3'b111;
        #200;

        a = 4'd11;
        b = 4'd8; // -Desplazamiento
        cin = 1;
        op = 3'b011;
        #200;      


                // --- TEST 2: Multiplicación (5 * 2 = 10) ---
        a = 4'b1110;
        b = 4'b0000;
        init = 1;
        #10;
        init = 0;
        op = 3'b010;  // Multiplicación
         #100;
        // Esperar hasta que el multiplicador indique que terminó
        wait (done == 1);
        #20;  

                // --- TEST 4: Resta simulada (9 - 4 = 5) usando complemento a 2 ---
        a = 4'd9;
        b = 4'd9; // -4 en complemento a 2
        cin = 1;
        op = 3'b001;
        #200;

        a = 4'd10;
        b = 4'd5; // -4 en complemento a 2
        cin = 1;
        op = 3'b111;
        #200;

        $display("=== Fin del test ===");
        $finish;
    end

endmodule

scr/alu_tb.vcd
$date
	Tue Oct  7 10:33:56 2025
$end
$version
	Icarus Verilog
$end
$timescale
	1ps
$end
$scope module alu_tb $end
$var wire 1 ! zero $end
$var wire 7 " result [6:0] $end
$var wire 1 # overflow $end
$var wire 1 $ done $end
$var wire 1 % carry $end
$var reg 4 & a [3:0] $end
$var reg 4 ' b [3:0] $end
$var reg 1 ( cin $end
$var reg 1 ) clk $end
$var reg 1 * init $end
$var reg 3 + op [2:0] $end
$scope module dut $end
$var wire 4 , a [3:0] $end
$var wire 4 - b [3:0] $end
$var wire 1 ( cin $end
$var wire 1 ) clk $end
$var wire 1 . done_ $end
$var wire 1 * init $end
$var wire 3 / op [2:0] $end
$var wire 7 0 sum_result [6:0] $end
$var wire 4 1 sum_ [3:0] $end
$var wire 7 2 shift_w [6:0] $end
$var wire 7 3 rest_result [6:0] $end
$var wire 8 4 mul_result [7:0] $end
$var wire 1 5 carry_ $end
$var reg 1 % carry $end
$var reg 1 $ done $end
$var reg 1 # overflow $end
$var reg 7 6 result [6:0] $end
$var reg 1 ! zero $end
$scope module mul $end
$var wire 4 7 a [3:0] $end
$var wire 4 8 b [3:0] $end
$var wire 1 ) clk $end
$var wire 1 * init $end
$var parameter 3 9 add $end
$var parameter 3 : check $end
$var parameter 3 ; finish $end
$var parameter 3 < shift $end
$var parameter 3 = star $end
$var reg 8 > a_copy [7:0] $end
$var reg 8 ? b_copy [7:0] $end
$var reg 1 @ done $end
$var reg 3 A next_state [2:0] $end
$var reg 8 B pp [7:0] $end
$var reg 8 C result [7:0] $end
$var reg 3 D state [2:0] $end
$upscope $end
$scope module sh $end
$var wire 4 E a [3:0] $end
$var wire 1 . done $end
$var wire 4 F shift_ [3:0] $end
$var wire 7 G shift_number [6:0] $end
$upscope $end
$scope module sum $end
$var wire 4 H a [3:0] $end
$var wire 4 I b [3:0] $end
$var wire 1 ( cin $end
$var wire 1 J clk $end
$var wire 1 K in0 $end
$var wire 1 L in1 $end
$var wire 1 M in2 $end
$var wire 1 N in3 $end
$var wire 4 O sum [3:0] $end
$var wire 1 P carry2 $end
$var wire 1 Q carry1 $end
$var wire 1 R carry0 $end
$var wire 1 5 carry $end
$scope module ad0 $end
$var wire 1 S a $end
$var wire 1 T ab_xor $end
$var wire 1 U and1 $end
$var wire 1 V and2 $end
$var wire 1 K b $end
$var wire 1 R carry $end
$var wire 1 ( cin $end
$var wire 1 W sum $end
$upscope $end
$scope module ad1 $end
$var wire 1 X a $end
$var wire 1 Y ab_xor $end
$var wire 1 Z and1 $end
$var wire 1 [ and2 $end
$var wire 1 L b $end
$var wire 1 Q carry $end
$var wire 1 R cin $end
$var wire 1 \ sum $end
$upscope $end
$scope module ad2 $end
$var wire 1 ] a $end
$var wire 1 ^ ab_xor $end
$var wire 1 _ and1 $end
$var wire 1 ` and2 $end
$var wire 1 M b $end
$var wire 1 P carry $end
$var wire 1 Q cin $end
$var wire 1 a sum $end
$upscope $end
$scope module ad3 $end
$var wire 1 b a $end
$var wire 1 c ab_xor $end
$var wire 1 d and1 $end
$var wire 1 e and2 $end
$var wire 1 N b $end
$var wire 1 5 carry $end
$var wire 1 P cin $end
$var wire 1 f sum $end
$upscope $end
$upscope $end
$upscope $end
$upscope $end
$enddefinitions $end
$comment Show the parameter values. $end
$dumpall
b0 =
b11 <
b100 ;
b1 :
b10 9
$end
#0
$dumpvars
0f
0e
0d
0c
0b
0a
0`
0_
0^
0]
0\
0[
0Z
0Y
0X
0W
0V
0U
0T
0S
0R
0Q
0P
b0 O
0N
0M
0L
0K
zJ
b0 I
b0 H
b0 G
b0 F
b0 E
bx D
bx C
bx B
bx A
x@
bx ?
bx >
b0 8
b0 7
bx 6
05
bx 4
b0 3
b0 2
b0 1
b0 0
b0 /
x.
b0 -
b0 ,
b0 +
0*
0)
0(
b0 '
b0 &
x%
x$
x#
bx "
x!
$end
#5000
0#
b0 "
b0 6
1)
#10000
1W
15
1T
1d
b1 3
b10001 0
b1 1
b1 O
0f
1K
1N
0c
1b
0)
b1 +
b1 /
b1001 '
b1001 -
b1001 8
b1001 F
b1001 I
b0 2
b0 G
b1000 &
b1000 ,
b1000 7
b1000 E
b1000 H
#15000
0!
1%
b10001 "
b10001 6
1)
#20000
0)
#25000
1)
#30000
1f
1Q
1P
1Z
1_
0W
1R
1\
b1110 3
b11110 0
b1110 1
b1110 O
1a
1L
1M
0T
1U
0Y
0^
1S
1X
1]
0)
1*
b1111 '
b1111 -
b1111 8
b1111 F
b1111 I
b1111 &
b1111 ,
b1111 7
b1111 E
b1111 H
#35000
b1 A
0%
0$
b0 "
b0 6
0@
b0 4
b0 C
b1111 ?
b1111 >
b0 B
b0 D
1)
#40000
0)
b10 +
b10 /
0*
#45000
b10 A
b1 D
x$
1!
1)
#50000
0)
#55000
b11 A
b10 D
1)
#60000
0)
#65000
b1 A
b11 D
b1111 B
1)
#70000
0)
#75000
b10 A
b111 ?
b11110 >
b1 D
1)
#80000
0)
#85000
b11 A
b10 D
1)
#90000
0)
#95000
b1 A
b101101 B
b11 D
1)
#100000
0)
#105000
b10 A
b1 D
b11 ?
b111100 >
1)
#110000
0)
#115000
b11 A
b10 D
1)
#120000
0)
#125000
b1 A
b11 D
b1101001 B
1)
#130000
0)
#135000
b10 A
b1 ?
b1111000 >
b1 D
1)
#140000
0)
#145000
b11 A
b10 D
1)
#150000
0)
#155000
b1 A
b11100001 B
b11 D
1)
#160000
0)
#165000
b11 A
b1 D
b0 ?
b11110000 >
1)
#170000
0)
#175000
b100 A
b11 D
1)
#180000
0)
#185000
b100 D
b11100000 >
1)
#190000
0)
#195000
1.
1@
b11100001 4
b11100001 C
1)
#200000
0)
#205000
1$
0!
b1100001 "
b1100001 6
1#
1)
#210000
0)
#215000
1)
#220000
0)
#225000
b1 A
b0 D
x.
0@
b0 4
b0 C
b1111 ?
b1111 >
b0 B
0$
0#
b0 "
b0 6
1)
1*
#230000
0)
#235000
b10 A
1%
b11110 "
b11110 6
b1001 ?
b1000 >
b1 D
0f
1W
0R
0\
0[
0Q
b1 3
b10001 0
b1 1
b1 O
0a
0`
0P
0L
0M
1T
0U
0Y
0Z
0^
0_
0S
0X
0]
1)
0*
b1 +
b1 /
b1001 '
b1001 -
b1001 8
b1001 F
b1001 I
b1000 &
b1000 ,
b1000 7
b1000 E
b1000 H
#240000
0)
#245000
b11 A
b10 D
b10001 "
b10001 6
1)
#250000
0)
#255000
b1 A
1!
b0 "
b0 6
b1000 B
b11 D
1a
1Q
1[
1Y
1R
0T
1U
1L
b101 3
b10101 0
b101 1
b101 O
1W
0V
1S
1)
1(
b10000 2
b10000 G
b100 '
b100 -
b100 8
b100 F
b100 I
b1001 &
b1001 ,
b1001 7
b1001 E
b1001 H
#260000
0)
#265000
b11 A
b1 D
b100 ?
b10000 >
0!
b101 "
b101 6
1)
#270000
0)
#275000
b1 A
b11 D
1)
#280000
0)
#285000
b11 A
b1 D
b10 ?
b100000 >
1)
#290000
0)
#295000
b1 A
b11 D
1)
#300000
0)
#305000
b10 A
b1 D
b1 ?
b1000000 >
1)
#310000
0)
#315000
b11 A
b10 D
1)
#320000
0)
#325000
b1 A
b11 D
b1001000 B
1)
#330000
0)
#335000
b11 A
b0 ?
b10000000 >
b1 D
1)
#340000
0)
#345000
b100 A
b11 D
1)
#350000
0)
#355000
b0 >
b100 D
1)
#360000
0)
#365000
1.
1@
b1001000 4
b1001000 C
1)
#370000
0)
#375000
1)
#380000
0)
#385000
1)
#390000
0)
#395000
1)
#400000
0)
#405000
1)
#410000
0)
#415000
1)
#420000
0)
#425000
1)
#430000
0)
#435000
1)
#440000
0)
#445000
1)
#450000
0)
#455000
1$
b1010 "
b1010 6
1a
1f
05
1Q
1c
0d
b1101 3
b1101 0
b1101 1
b1101 O
0\
1[
0L
0N
1Y
0Z
1X
1)
b111 +
b111 /
b1110 '
b1110 -
b1110 8
b1110 F
b1110 I
b0 2
b0 G
b1011 &
b1011 ,
b1011 7
b1011 E
b1011 H
#460000
0)
#465000
1)
#470000
0)
#475000
1)
#480000
0)
#485000
1)
#490000
0)
#495000
1)
#500000
0)
#505000
1)
#510000
0)
#515000
1)
#520000
0)
#525000
1)
#530000
0)
#535000
1)
#540000
0)
#545000
1)
#550000
0)
#555000
1)
#560000
0)
#565000
1)
#570000
0)
#575000
1)
#580000
0)
#585000
1)
#590000
0)
#595000
1)
#600000
0)
#605000
1)
#610000
0)
#615000
1)
#620000
0)
#625000
1)
#630000
0)
#635000
1)
#640000
0)
#645000
1)
#650000
0)
#655000
1!
b0 "
b0 6
15
0f
1e
1P
1\
0[
b11 3
b10011 0
b11 1
b11 O
0a
1`
0Y
1Z
1^
1L
1M
1)
b11 +
b11 /
b1000 '
b1000 -
b1000 8
b1000 F
b1000 I
#660000
0)
#665000
1)
#670000
0)
#675000
1)
#680000
0)
#685000
1)
#690000
0)
#695000
1)
#700000
0)
#705000
1)
#710000
0)
#715000
1)
#720000
0)
#725000
1)
#730000
0)
#735000
1)
#740000
0)
#745000
1)
#750000
0)
#755000
1)
#760000
0)
#765000
1)
#770000
0)
#775000
1)
#780000
0)
#785000
1)
#790000
0)
#795000
1)
#800000
0)
#805000
1)
#810000
0)
#815000
1)
#820000
0)
#825000
1)
#830000
0)
#835000
1)
#840000
0)
#845000
1)
#850000
0)
#855000
b1 A
0%
0$
x.
0@
b0 4
b0 C
b1110 >
b0 B
b0 D
1f
0e
1\
0c
1d
0W
1V
1R
b1110 3
b11110 0
b1110 1
b1110 O
1a
0`
1N
1T
0U
0^
1_
0S
1]
1)
1*
b1110 2
b1110 G
b0 '
b0 -
b0 8
b0 F
b0 I
b1110 &
b1110 ,
b1110 7
b1110 E
b1110 H
#860000
0)
#865000
b11 A
b1 D
x$
1)
b10 +
b10 /
0*
#870000
0)
#875000
b100 A
b11 D
1)
#880000
0)
#885000
b100 D
b11100 >
1)
#890000
0)
#895000
1.
1@
1)
#900000
0)
#905000
1$
1)
#910000
0)
#915000
1)
#920000
0)
#925000
1)
#930000
0)
#935000
1)
#940000
0)
#945000
1)
#950000
0)
#955000
1)
#960000
0)
#965000
1)
#970000
0)
#975000
1)
#980000
0)
#985000
0!
1%
b1110 "
b1110 6
0f
1e
15
1R
1c
0d
0W
1V
0\
1[
1Q
b0 3
b10000 0
b0 1
b0 O
0a
1`
1P
0K
0N
1T
0U
1Y
0Z
1^
0_
1S
0X
0]
1)
b1 +
b1 /
b1001 '
b1001 -
b1001 8
b1001 F
b1001 I
b0 2
b0 G
b1001 &
b1001 ,
b1001 7
b1001 E
b1001 H
#990000
0)
#995000
1!
b0 "
b0 6
1)
#1000000
0)
#1005000
1)
#1010000
0)
#1015000
1)
#1020000
0)
#1025000
1)
#1030000
0)
#1035000
1)
#1040000
0)
#1045000
1)
#1050000
0)
#1055000
1)
#1060000
0)
#1065000
1)
#1070000
0)
#1075000
1)
#1080000
0)
#1085000
1)
#1090000
0)
#1095000
1)
#1100000
0)
#1105000
1)
#1110000
0)
#1115000
1)
#1120000
0)
#1125000
1)
#1130000
0)
#1135000
1)
#1140000
0)
#1145000
1)
#1150000
0)
#1155000
1)
#1160000
0)
#1165000
1)
#1170000
0)
#1175000
1)
#1180000
0)
#1185000
0P
1a
0`
0f
0e
0R
0^
0c
1d
1W
0V
b101 3
b10101 0
b101 1
b101 O
0\
0[
0M
1N
0T
0Y
1Z
0S
1X
1)
b111 +
b111 /
b1000000 2
b1000000 G
b101 '
b101 -
b101 8
b101 F
b101 I
b1010 &
b1010 ,
b1010 7
b1010 E
b1010 H
